python_zte_mc801a/__init__.py
python_zte_mc801a/client/__init__.py
python_zte_mc801a/client/data_io.py
python_zte_mc801a/client/live.py
python_zte_mc801a/lib/__init__.py
python_zte_mc801a/lib/constants.py
python_zte_mc801a/lib/data_processing.py
python_zte_mc801a/lib/helpers.py
python_zte_mc801a/lib/router_requests.py
python_zte_mc801a/main.py
python_zte_mc801a-0.1.0.dist-info/WHEEL
python_zte_mc801a-0.1.0.dist-info/entry_points.txt
python_zte_mc801a-0.1.0.dist-info/METADATA
python_zte_mc801a-0.1.0.dist-info/RECORD
