Metadata-Version: 2.1
Name: python-zte-mc801a
Version: 0.1.0
Summary: 
Home-page: https://github.com/nicjac/python-zte-mc801a
Author: Nicolas Jaccard
Author-email: nicolas.jaccard@gmail.com
Requires-Python: >=3.9,<4.0
Classifier: Programming Language :: Python :: 3
Classifier: Programming Language :: Python :: 3.9
Classifier: Programming Language :: Python :: 3.10
Classifier: Programming Language :: Python :: 3.11
Requires-Dist: pyyaml (>=6.0,<7.0)
Requires-Dist: requests (>=2.28.2,<3.0.0)
Requires-Dist: retry (>=0.9.2,<0.10.0)
Requires-Dist: termplotlib (>=0.3.9,<0.4.0)
Requires-Dist: typer[all] (>=0.7.0,<0.8.0)
Project-URL: Repository, https://github.com/nicjac/python-zte-mc801a
